CoolMemoryEnglish.py
coolmemoryenglish-1.0.0.2.dist-info/WHEEL
coolmemoryenglish-1.0.0.2.dist-info/METADATA
coolmemoryenglish-1.0.0.2.dist-info/RECORD
