Metadata-Version: 2.1
Name: CoolMemoryEnglish
Version: 1.0.0.2
Summary: CoolMemory-English 是一个免费的记单词软件，它在传统的记单词方式（听、说、读、写）之外提供了一种新的方式：敲
Keywords: 英语,单词,English,CoolMemory-English,CoolMemoryEnglish
Author-email: "lcctoor.com" <lcctoor@outlook.com>
Project-URL: HomePage, https://github.com/lcctoor/arts/tree/main/arts/CoolMemory-English
